odoo10_addon_help_online-10.0.1.0.0.99.dev15-py2.7-nspkg.pth
odoo/addons/help_online/README.rst
odoo/addons/help_online/__init__.py
odoo/addons/help_online/__manifest__.py
odoo/addons/help_online/controllers/__init__.py
odoo/addons/help_online/controllers/help_online_controllers.py
odoo/addons/help_online/data/help_auto_backup.sample
odoo/addons/help_online/data/ir_config_parameter_data.xml
odoo/addons/help_online/i18n/ar.po
odoo/addons/help_online/i18n/de.po
odoo/addons/help_online/i18n/es.po
odoo/addons/help_online/i18n/eu.po
odoo/addons/help_online/i18n/fi.po
odoo/addons/help_online/i18n/fr.po
odoo/addons/help_online/i18n/help_online.pot
odoo/addons/help_online/i18n/hr.po
odoo/addons/help_online/i18n/it.po
odoo/addons/help_online/i18n/nl.po
odoo/addons/help_online/i18n/nl_NL.po
odoo/addons/help_online/i18n/pt.po
odoo/addons/help_online/i18n/pt_BR.po
odoo/addons/help_online/i18n/ro.po
odoo/addons/help_online/i18n/sl.po
odoo/addons/help_online/i18n/tr.po
odoo/addons/help_online/models/__init__.py
odoo/addons/help_online/models/help_online.py
odoo/addons/help_online/models/ir_model.py
odoo/addons/help_online/security/help_online_groups.xml
odoo/addons/help_online/security/help_online_rules.xml
odoo/addons/help_online/static/description/help_online_create_page.png
odoo/addons/help_online/static/description/help_online_view_page.png
odoo/addons/help_online/static/description/icon.png
odoo/addons/help_online/static/description/index.html
odoo/addons/help_online/static/src/css/help_online.css
odoo/addons/help_online/static/src/img/snippet/snippet_thumbs.png
odoo/addons/help_online/static/src/js/help_online.js
odoo/addons/help_online/static/src/xml/help_online.xml
odoo/addons/help_online/tests/__init__.py
odoo/addons/help_online/tests/common.py
odoo/addons/help_online/tests/test_export_help_wizard.py
odoo/addons/help_online/tests/test_help_online.py
odoo/addons/help_online/tests/test_import_help_wizard.py
odoo10_addon_help_online-10.0.1.0.0.99.dev15.dist-info/DESCRIPTION.rst
odoo10_addon_help_online-10.0.1.0.0.99.dev15.dist-info/METADATA
odoo10_addon_help_online-10.0.1.0.0.99.dev15.dist-info/RECORD
odoo10_addon_help_online-10.0.1.0.0.99.dev15.dist-info/WHEEL
odoo10_addon_help_online-10.0.1.0.0.99.dev15.dist-info/metadata.json
odoo10_addon_help_online-10.0.1.0.0.99.dev15.dist-info/namespace_packages.txt
odoo10_addon_help_online-10.0.1.0.0.99.dev15.dist-info/top_level.txt
